README.txt
setup.py
colorDetect/__init__.py
colorDetect/colorDetect.py
colordetectionwoiiiiiii.egg-info/PKG-INFO
colordetectionwoiiiiiii.egg-info/SOURCES.txt
colordetectionwoiiiiiii.egg-info/dependency_links.txt
colordetectionwoiiiiiii.egg-info/requires.txt
colordetectionwoiiiiiii.egg-info/top_level.txt