Metadata-Version: 2.1
Name: colordetectionwoiiiiiii
Version: 0.0.1
Summary: Color detection
Home-page: UNKNOWN
Author: Iqqy
Author-email: akhmdashdq@gmail.com
License: UNKNOWN
Keywords: python,video,stream,video stream,camera stream
Platform: UNKNOWN
Classifier: Development Status :: 1 - Planning
Classifier: Intended Audience :: Education
Classifier: Programming Language :: Python :: 3
Classifier: Operating System :: Unix
Classifier: Operating System :: MacOS :: MacOS X
Classifier: Operating System :: Microsoft :: Windows
